assets/dual_display_background.png
assets/keyboard-azerty.svg
assets/keyboard-dvorak.svg
assets/keyboard-en.svg
assets/keyboard-engr.svg
assets/keyboard-enjp.svg
assets/keyboard-gr.svg
assets/keyboard-jp.svg
assets/keyboard-qwerty-azerty.svg
assets/keyboard-qwerty-dvorak.svg
assets/mono_display_background.png
layouts/azerty.yml
layouts/dvorak.yml
layouts/en.yml
layouts/engr.yml
layouts/enjp.yml
layouts/gr.yml
layouts/jp.yml
layouts/qwerty_azerty.yml
layouts/qwerty_dvorak.yml
typingvid.py
typingvid-0.1.1.dist-info/entry_points.txt
typingvid-0.1.1.dist-info/LICENSE
typingvid-0.1.1.dist-info/WHEEL
typingvid-0.1.1.dist-info/METADATA
typingvid-0.1.1.dist-info/RECORD
