Metadata-Version: 2.1
Name: typingvid
Version: 0.1.1
Summary: An open-source, simple but extensible typing animation generator.
Home-page: https://www.gavalas.dev/projects/typingvid
License: MIT
Keywords: keyboard,animation,command-line utility
Author: Konstantinos Gavalas
Author-email: contact@gavalas.dev
Requires-Python: >=3.10,<4.0
Classifier: Development Status :: 5 - Production/Stable
Classifier: Environment :: Console
Classifier: License :: OSI Approved :: MIT License
Classifier: Natural Language :: English
Classifier: Natural Language :: Greek
Classifier: Natural Language :: Japanese
Classifier: Programming Language :: Python :: 3
Classifier: Programming Language :: Python :: 3.10
Classifier: Topic :: Multimedia :: Video
Classifier: Topic :: Utilities
Requires-Dist: CairoSVG (>=2.5.2,<3.0.0)
Requires-Dist: PyYAML (>=6.0,<7.0)
Requires-Dist: bs4 (>=0.0.1,<0.0.2)
Requires-Dist: lxml (>=4.9.1,<5.0.0)
Requires-Dist: moviepy (>=1.0.3,<2.0.0)
Project-URL: Repository, https://github.com/GavalasDev/typingvid
